{
  "version": "1.61.16",
  "pub_date": "2026-05-13T06:17:38.995Z",
  "platforms": {
    "macos": {
      "url": "https://github.com/KandiForge/distribution/releases/download/spectacle-gui-v1.61.16/Spectacle_1.61.16_universal.dmg",
      "filename": "Spectacle_1.61.16_universal.dmg"
    },
    "windows": {
      "url": "https://github.com/KandiForge/distribution/releases/download/spectacle-gui-v1.61.16/Spectacle_1.61.16_x64-setup.exe",
      "filename": "Spectacle_1.61.16_x64-setup.exe"
    }
  }
}